viggolocal/__init__.py
viggolocal/resources.py
viggolocal/subsystem/__init__.py
viggolocal/subsystem/common/__init__.py
viggolocal/subsystem/common/endereco/__init__.py
viggolocal/subsystem/common/endereco/resource.py
viggolocal/subsystem/parametrizacao/__init__.py
viggolocal/subsystem/parametrizacao/localidade/__init__.py
viggolocal/subsystem/parametrizacao/localidade/mesorregiao/__init__.py
viggolocal/subsystem/parametrizacao/localidade/mesorregiao/resource.py
viggolocal/subsystem/parametrizacao/localidade/microrregiao/__init__.py
viggolocal/subsystem/parametrizacao/localidade/microrregiao/resource.py
viggolocal/subsystem/parametrizacao/localidade/municipio/__init__.py
viggolocal/subsystem/parametrizacao/localidade/municipio/resource.py
viggolocal/subsystem/parametrizacao/localidade/pais/__init__.py
viggolocal/subsystem/parametrizacao/localidade/pais/resource.py
viggolocal/subsystem/parametrizacao/localidade/regiao/__init__.py
viggolocal/subsystem/parametrizacao/localidade/regiao/resource.py
viggolocal/subsystem/parametrizacao/localidade/uf/__init__.py
viggolocal/subsystem/parametrizacao/localidade/uf/resource.py
viggolocal/subsystem/sysadmin/__init__.py
viggolocal/subsystem/sysadmin/ibge_sync/__init__.py
viggolocal/subsystem/sysadmin/ibge_sync/manager.py
viggolocal/subsystem/sysadmin/ibge_sync/resource.py
viggolocal-1.1.2.dist-info/AUTHORS
viggolocal-1.1.2.dist-info/METADATA
viggolocal-1.1.2.dist-info/WHEEL
viggolocal-1.1.2.dist-info/top_level.txt
viggolocal-1.1.2.dist-info/RECORD
